README.rst
setup.py
src/pydentifier/__init__.py
src/pydentifier/base.py
src/pydentifier.egg-info/PKG-INFO
src/pydentifier.egg-info/SOURCES.txt
src/pydentifier.egg-info/dependency_links.txt
src/pydentifier.egg-info/top_level.txt
src/pydentifier/en/__init__.py
src/pydentifier/en/contractions.py